{
    "name": "hb_leisure_overnight",
    "orig": "home",
    "dest": "leisure",
    "generation_area": "domestic",
    "attraction_area": "domestic",
    "struct": "mode>dest",
    "gen_model": "rate",
    "generation": {
        "no_car": {
            "age_7_17": 0.0545,
            "age_18_29": 0.063,
            "age_30_49": 0.0203,
            "age_50_64": 0.0213,
            "age_65_99": 0.0158
        },
        "has_car": {
            "age_7_17": 0.0343,
            "age_18_29": 0.0461,
            "age_30_49": 0.0284,
            "age_50_64": 0.0381,
            "age_65_99": 0.0334
        }
    },
    "impedance_share": {
        "walk": {
            "vrk": [
                1.0,
                1.0
              ]
            },
        "car_leisure": {
            "vrk": [
                1.0,
                1.0
              ]
            },
        "car_pax": {
            "vrk": [
                1.0,
                1.0
              ]
            },
        "airplane": {
            "vrk": [
                1.0,
                1.0
              ]
            },
        "transit_leisure": {
            "vrk": [
                1.0,
                1.0
              ]
            },
        "airpl_car_acc": {
            "vrk": [
                2.0,
                0.0
                ]
            },
        "airpl_car_egr": {
            "vrk": [
                2.0,
                0.0
                ]
            },
        "pt_car_acc": {
            "vrk": [
                2.0,
                0.0
                ]
            },
        "pt_taxi_acc": {
            "vrk": [
                2.0,
                0.0
                ]
            },
        "pt_taxi_egr": {
            "vrk": [
                2.0,
                0.0
                ]
            }
    },
    "distance_boundaries": {
        "walk": [
            0,
            30
        ],
        "car_leisure": [
            0,
            9999
        ],
        "car_pax": [
            0,
            9999
        ],
        "airplane": [
            0,
            9999
        ],
        "airpl_car_acc": [
            0,
            9999
        ],
        "airpl_taxi_acc": [
            0,
            9999
        ],
        "airpl_car_egr": [
            0,
            9999
        ],
        "transit_leisure": [
            0,
            9999
        ],
        "pt_car_acc": [
            0,
            9999
        ],
        "pt_taxi_acc": [
            0,
            9999
        ],
        "pt_taxi_egr": [
            0,
            9999
        ]
    },
    "destination_choice": {
        "airplane": {
            "attraction": {
                "within_zone_inf": -1
            },
            "impedance": {
                "logsum": 0.4208
            },
            "log": {
                "attraction_size": 1
            },
            "attraction_size": {
                "area_leisure_buildings": 1,
                "wrk_hospitality*beeline_0_100_km": 20.84262,
                "wrk_hospitality*beeline_100_200_km": 97.70962,
                "wrk_hospitality*beeline_200_400_km": 325.05682,
                "wrk_hospitality*beeline_400_600_km": 765.09499,
                "wrk_hospitality*beeline_600_9999_km": 9311.44903,
                "population*beeline_0_100_km": 1.6446,
                "population*beeline_100_200_km": 2.17907,
                "population*beeline_200_400_km": 4.88906,
                "population*beeline_400_600_km": 11.02318,
                "population*beeline_600_9999_km": 138.65655
            }
        },
        "transit_leisure": {
            "attraction": {
                "within_zone_inf": -1
            },
            "impedance": {
                "logsum": 0.4208
            },
            "log": {
                "attraction_size": 1
            },
            "attraction_size": {
                "area_leisure_buildings": 1,
                "wrk_hospitality*beeline_0_100_km": 20.84262,
                "wrk_hospitality*beeline_100_200_km": 97.70962,
                "wrk_hospitality*beeline_200_400_km": 325.05682,
                "wrk_hospitality*beeline_400_600_km": 765.09499,
                "wrk_hospitality*beeline_600_9999_km": 9311.44903,
                "population*beeline_0_100_km": 1.6446,
                "population*beeline_100_200_km": 2.17907,
                "population*beeline_200_400_km": 4.88906,
                "population*beeline_400_600_km": 11.02318,
                "population*beeline_600_9999_km": 138.65655
            }
        },
        "car_leisure": {
            "attraction": {
                "within_zone_inf": -1
            },
            "impedance": {
                "gen_cost": -0.01238
            },
            "log": {
                "attraction_size": 1,
                "gen_cost": -1.278
            },
            "attraction_size": {
                "area_leisure_buildings": 1,
                "wrk_hospitality*beeline_0_100_km": 20.84262,
                "wrk_hospitality*beeline_100_200_km": 97.70962,
                "wrk_hospitality*beeline_200_400_km": 325.05682,
                "wrk_hospitality*beeline_400_600_km": 765.09499,
                "wrk_hospitality*beeline_600_9999_km": 9311.44903,
                "population*beeline_0_100_km": 1.6446,
                "population*beeline_100_200_km": 2.17907,
                "population*beeline_200_400_km": 4.88906,
                "population*beeline_400_600_km": 11.02318,
                "population*beeline_600_9999_km": 138.65655
            }
        },
        "car_pax": {
            "attraction": {
                "within_zone_inf": -1
            },
            "impedance": {
                "gen_cost": -0.01383
            },
            "log": {
                "attraction_size": 1,
                "gen_cost": -1.335
            },
            "attraction_size": {
                "area_leisure_buildings": 1,
                "wrk_hospitality*beeline_0_100_km": 20.84262,
                "wrk_hospitality*beeline_100_200_km": 97.70962,
                "wrk_hospitality*beeline_200_400_km": 325.05682,
                "wrk_hospitality*beeline_400_600_km": 765.09499,
                "wrk_hospitality*beeline_600_9999_km": 9311.44903,
                "population*beeline_0_100_km": 1.6446,
                "population*beeline_100_200_km": 2.17907,
                "population*beeline_200_400_km": 4.88906,
                "population*beeline_400_600_km": 11.02318,
                "population*beeline_600_9999_km": 138.65655
            }
        },
        "walk": {
            "attraction": {
                "within_zone_inf": -1
            },
            "impedance": {
                "dist": -0.3449
            },
            "log": {
                "attraction_size": 1    
            },
            "attraction_size": {
                "area_leisure_buildings": 1,
                "wrk_hospitality*beeline_0_100_km": 20.84262,
                "wrk_hospitality*beeline_100_200_km": 97.70962,
                "wrk_hospitality*beeline_200_400_km": 325.05682,
                "wrk_hospitality*beeline_400_600_km": 765.09499,
                "wrk_hospitality*beeline_600_9999_km": 9311.44903,
                "population*beeline_0_100_km": 1.6446,
                "population*beeline_100_200_km": 2.17907,
                "population*beeline_200_400_km": 4.88906,
                "population*beeline_400_600_km": 11.02318,
                "population*beeline_600_9999_km": 138.65655
            }
        }
    },
    "mode_choice": {
        "airplane": {
            "constant": 0,
            "generation": {},
            "attraction": {},
            "impedance": {},
            "log": {
                "logsum": 0.1182
            },
            "individual_dummy": {}
        },
        "transit_leisure": {
            "constant": 18.15,
            "generation": {},
            "attraction": {},
            "impedance": {},
            "log": {
                "logsum": 0.1182
            },
            "individual_dummy": {}
        },
        "car_leisure": {
            "constant": 4.814,
            "generation": {},
            "attraction": {},
            "impedance": {},
            "log": {
                "logsum": 0.1182
            },
            "individual_dummy": {
                "sh_cars1_hh1": 31.1,
                "sh_cars2_hh2": 31.1,
                "sh_cars1_hh2": 29.02
            }
        },
        "car_pax": {
            "constant": 20.43,
            "generation": {},
            "attraction": {},
            "impedance": {},
            "log": {
                "logsum": 0.1182
            },
            "individual_dummy": {
                "sh_cars1_hh2": 12.86,
                "sh_cars2_hh2": 12.86
            }
        },
        "walk": {
            "constant": 18.34,
            "generation": {},
            "attraction": {},
            "impedance": {},
            "log": {
                "logsum": 0.1182
            },
            "individual_dummy": {}
        },
        "scaling": {
            "car_leisure": {
                "constant": 0.1182,
                "individual_dummy": {
                    "sh_cars1_hh1": 0.1182,
                    "sh_cars2_hh2": 0.1182,
                    "sh_cars1_hh2": 0.1182
                }
            },
            "car_pax": {
                "constant": 0.1182,
                "individual_dummy": {
                    "sh_cars1_hh2": 0.1182,
                    "sh_cars2_hh2": 0.1182
                }
            },
            "transit_leisure": {
                "constant": 0.1182
            },
            "airplane": {
                "constant": 0.1182
            },
            "walk": {
                "constant": 0.1182
            }
        }
    },
    "access_mode_choice": {
        "airplane": {
            "airplane": {
                "constant": -2,
                "generation": {},
                "attraction": {},
                "impedance": {
                    "gen_cost": -0.04309
                },
                "log": {
                    "transform": -1.982
                },
                "transform": {
                    "attraction": {},
                    "impedance": {
                        "gen_cost": 1
                    }
                },
                "individual_dummy": {}
            },
            "airpl_car_acc": {
                "constant": -5.688,
                "generation": {},
                "attraction": {},
                "impedance": {
                    "gen_cost": -0.04309
                },
                "log": {
                    "transform": -1.982
                },
                "transform": {
                    "attraction": {},
                    "impedance": {
                        "gen_cost": 1
                    }
                },
                "individual_dummy": {
                    "sh_cars1_hh1": 4.218,
                    "sh_cars2_hh2": 4.218,
                    "sh_cars1_hh2": 3.2
                }
            },
            "airpl_taxi_acc": {
                "constant": -3.313,
                "generation": {},
                "attraction": {},
                "impedance": {
                    "gen_cost": -0.04309
                },
                "log": {
                    "transform": -1.982
                },
                "transform": {
                    "attraction": {},
                    "impedance": {
                        "gen_cost": 1
                    }
                },
                "individual_dummy": {
                    "sh_cars1_hh2": 1.578,
                    "sh_cars2_hh2": 1.578
                }
            },
            "airpl_car_egr": {
                "constant": -3.036,
                "generation": {},
                "attraction": {},
                "impedance": {
                    "gen_cost": -0.04309
                },
                "log": {
                    "transform": -1.982
                },
                "transform": {
                    "attraction": {},
                    "impedance": {
                        "gen_cost": 1
                    }
                },
                "individual_dummy": {}
            }
        },
        "transit_leisure": {
            "transit_leisure": {
                "constant": 0,
                "generation": {},
                "attraction": {},
                "impedance": {
                    "gen_cost": -0.04309
                },
                "log": {
                    "transform": -1.982
                },
                "transform": {
                    "attraction": {},
                    "impedance": {
                        "gen_cost": 1
                    }
                },
                "individual_dummy": {}
            },
            "pt_car_acc": {
                "constant": -5.688,
                "generation": {},
                "attraction": {},
                "impedance": {
                    "gen_cost": -0.04309
                },
                "log": {
                    "transform": -1.982
                },
                "transform": {
                    "attraction": {},
                    "impedance": {
                        "gen_cost": 1
                    }
                },
                "individual_dummy": {
                    "sh_cars1_hh1": 4.218,
                    "sh_cars2_hh2": 4.218,
                    "sh_cars1_hh2": 3.2
                }
            },
            "pt_taxi_acc": {
                "constant": -3.313,
                "generation": {},
                "attraction": {},
                "impedance": {
                    "gen_cost": -0.04309
                },
                "log": {
                    "transform": -1.982
                },
                "transform": {
                    "attraction": {},
                    "impedance": {
                        "gen_cost": 1
                    }
                },
                "individual_dummy": {
                    "sh_cars1_hh2": 1.578,
                    "sh_cars2_hh2": 1.578
                }
            },
            "pt_taxi_egr": {
                "constant": -3.036,
                "generation": {},
                "attraction": {},
                "impedance": {
                    "gen_cost": -0.04309
                },
                "log": {
                    "transform": -1.982
                },
                "transform": {
                    "attraction": {},
                    "impedance": {
                        "gen_cost": 1
                    }
                },
                "individual_dummy": {}
            }
        }
    },
    "demand_share": {
        "walk": {
            "vrk": [
                1.0,
                1.0
              ]
        },
        "car_leisure": {
            "vrk": [
                1.0,
                1.0
              ]
        },
        "car_pax": {
            "vrk": [
                1.0,
                1.0
              ]
        },
        "airplane": {
            "vrk": [
                1.0,
                1.0
              ]
        },
        "transit_leisure": {
            "vrk": [
                1.0,
                1.0
              ]
        },
        "airpl_car_acc": {
            "vrk": [
                1.0,
                0.0
              ]
        },
        "pt_car_acc": {
            "vrk": [
                1.0,
                0.0
              ]
        },
        "pt_taxi_acc": {
            "vrk": [
                1.0,
                0.0
              ]
        },
        "airpl_car_egr": {
            "vrk": [
                0.0,
                1.0
                ]
        },
        "pt_car_egr": {
            "vrk": [
                0.0,
                1.0
                ]
        },
        "pt_taxi_egr": {
            "vrk": [
                0.0,
                1.0
                ]
        }
    }
}
